.gitignore
MANIFEST.in
README.md
requirements.txt
result.out
setup.cfg
setup.py
data/data.in
docs/rolodex_instructions.pages
docs/rolodex_instructions.pdf
rolodexer/__init__.py
rolodexer/cli.py
rolodexer/histogram.py
rolodexer/parser.py
rolodexer.egg-info/PKG-INFO
rolodexer.egg-info/SOURCES.txt
rolodexer.egg-info/dependency_links.txt
rolodexer.egg-info/entry_points.txt
rolodexer.egg-info/requires.txt
rolodexer.egg-info/top_level.txt
rolodexer/legacy/__init__.py
rolodexer/legacy/test_rolodexer.py
test/__init__.py
test/test_rolodexer.py