Metadata-Version: 1.1
Name: rolodexer
Version: 0.1.2
Summary: Parse rolodex data and output JSON
Home-page: http://bitbucket.org/fish2000/rolodexer
Author: Alexander Bohn
Author-email: fish2000@gmail.com
License: GPLv2
Download-URL: http://bitbucket.org/fish2000/rolodexer/zipball/master
Keywords: JSON,CSV,rolodex,contact,database,parse
Platform: any
Classifier: Development Status :: 5 - Production/Stable
Classifier: Environment :: Other Environment
Classifier: Environment :: Plugins
Classifier: Intended Audience :: Developers
Classifier: License :: OSI Approved :: BSD License
Classifier: Topic :: Database
Classifier: Topic :: Utilities
Classifier: License :: OSI Approved :: GNU General Public License (GPL)
Classifier: Operating System :: MacOS
Classifier: Operating System :: Microsoft :: Windows
Classifier: Operating System :: OS Independent
Classifier: Operating System :: POSIX
Classifier: Operating System :: Unix
Classifier: Programming Language :: Python :: 2.6
Classifier: Programming Language :: Python :: 2.7
Classifier: Programming Language :: Python :: Implementation :: PyPy
